authlier_flask/__init__.py
authlier_flask-1.0.1.dist-info/METADATA
authlier_flask-1.0.1.dist-info/WHEEL
authlier_flask-1.0.1.dist-info/licenses/LICENSE
authlier_flask-1.0.1.dist-info/RECORD
