Metadata-Version: 2.4
Name: authlier-flask
Version: 1.0.1
Summary: Authlier flask plugin
Project-URL: Homepage, https://github.com/beiller/authlier-flask
Project-URL: Issues, https://github.com/beiller/authlier-flask/issues
Author-email: Bill Hamilton <beiller@gmail.com>
License-Expression: MIT
License-File: LICENSE
Classifier: Operating System :: OS Independent
Classifier: Programming Language :: Python :: 3
Requires-Python: >=3.2
